{
    "SEVEN": {
        "average": "0:56:50",
        "std_dev": "0:15:25"
    },
    "TWELVE": {
        "average": "0:25:19",
        "std_dev": "0:08:52"
    },
    "TWO": {
        "average": "0:50:34",
        "std_dev": "0:10:15"
    },
    "THREE": {
        "average": "1:30:20",
        "std_dev": "0:58:27"
    },
    "TEN": {
        "average": "0:46:29",
        "std_dev": "0:28:09"
    },
    "FIFTEEN": {
        "average": "0:11:05",
        "std_dev": "0:06:23"
    },
    "ELEVEN": {
        "average": "0:21:59",
        "std_dev": "0:05:16"
    },
    "FOURTEEN": {
        "average": "0:31:43",
        "std_dev": "0:22:05"
    },
    "NINE": {
        "average": "0:22:18",
        "std_dev": "0:05:28"
    },
    "FOUR": {
        "average": "0:29:30",
        "std_dev": "0:06:30"
    },
    "THIRTEEN": {
        "average": "1:13:10",
        "std_dev": "0:26:50"
    },
    "ONE": {
        "average": "0:18:21",
        "std_dev": "0:05:29"
    },
    "EIGHT": {
        "average": "0:31:11",
        "std_dev": "0:09:08"
    },
    "SIX": {
        "average": "1:11:50",
        "std_dev": "0:00:00"
    }
}