{
    "SEVEN": {
        "average_seconds": 5.67
    },
    "TWO": {
        "average_seconds": 4.72
    },
    "TWELVE": {
        "average_seconds": 5.81
    },
    "THREE": {
        "average_seconds": 4.77
    },
    "TEN": {
        "average_seconds": 2.14
    },
    "THIRTEEN": {
        "average_seconds": 2.32
    },
    "ELEVEN": {
        "average_seconds": 2.4
    },
    "FOURTEEN": {
        "average_seconds": 1.12
    },
    "FIFTEEN": {
        "average_seconds": 4.31
    },
    "NINE": {
        "average_seconds": 0.48
    },
    "ONE": {
        "average_seconds": 5.58
    },
    "FOUR": {
        "average_seconds": 5.66
    },
    "EIGHT": {
        "average_seconds": 1.28
    }
}